pylint_websockets/__init__.py
pylint_websockets-0.1.2.dist-info/METADATA
pylint_websockets-0.1.2.dist-info/WHEEL
pylint_websockets-0.1.2.dist-info/RECORD
