Metadata-Version: 2.1
Name: pylint-websockets
Version: 0.1.2
Summary: A Pylint plugin for the Python websockets library
Home-page: https://github.com/ThatXliner/pylint-websockets
Author: Bryan Hu
Author-email: bryan.hu.2020@gmail.com
Requires-Python: >=3.7
Classifier: Programming Language :: Python :: 3
Classifier: Programming Language :: Python :: 3.7
Classifier: Programming Language :: Python :: 3.8
Classifier: Programming Language :: Python :: 3.9
Classifier: Programming Language :: Python :: 3.10
Classifier: Programming Language :: Python :: 3.11
Requires-Dist: pylint
Requires-Dist: websockets
